alaspo/__init__.py
alaspo/__main__.py
alaspo/__version__.py
alaspo/config.py
alaspo/initial.py
alaspo/json_config.py
alaspo/lns.py
alaspo/relax.py
alaspo/search.py
alaspo/solver.py
alaspo/strategy.py
alaspo/tuning.py
alaspo/tuning_util.py
alaspo-0.3.dist-info/licenses/LICENSE
alaspo-0.3.dist-info/METADATA
alaspo-0.3.dist-info/WHEEL
alaspo-0.3.dist-info/entry_points.txt
alaspo-0.3.dist-info/top_level.txt
alaspo-0.3.dist-info/RECORD
